README.md
setup.cfg
setup.py
bsc/__init__.py
bsc/db_classes.py
bsc/db_init_file.py
bsc/db_populate.py
bsc/main.py
bsc/user.py
python_bsc.egg-info/PKG-INFO
python_bsc.egg-info/SOURCES.txt
python_bsc.egg-info/dependency_links.txt
python_bsc.egg-info/requires.txt
python_bsc.egg-info/top_level.txt