Metadata-Version: 2.1
Name: python-bsc
Version: 0.0.3a0
Summary: A python based balanced scorecard implementation for managing objectives, tracking KPIs and improving organisational performance
Home-page: https://github.com/PandaCarl/python-bsc
Author: Carl du Plessis
Author-email: 
License: MIT
Download-URL: https://github.com/PandaCarl/python-bsc/archive/refs/tags/0.0.3alpha.tar.gz
Keywords: Balanced Scorecard,KPI's,Performance management
Platform: UNKNOWN
Classifier: Development Status :: 1 - Planning
Classifier: Intended Audience :: Developers
Classifier: Topic :: Software Development :: Build Tools
Classifier: License :: OSI Approved :: MIT License
Classifier: Programming Language :: Python :: 3
